LICENSE
pycommons/__init__.py
pycommons/base/__init__.py
pycommons/base/atomic/__init__.py
pycommons/base/atomic/atomic.py
pycommons/base/atomic/boolean.py
pycommons/base/atomic/integer.py
pycommons/base/char.py
pycommons/base/concurrent/__init__.py
pycommons/base/concurrent/exception.py
pycommons/base/concurrent/executor/__init__.py
pycommons/base/concurrent/executor/direct.py
pycommons/base/concurrent/executor/executors.py
pycommons/base/concurrent/future/__init__.py
pycommons/base/concurrent/future/callback.py
pycommons/base/container/__init__.py
pycommons/base/container/boolean.py
pycommons/base/container/container.py
pycommons/base/container/integer.py
pycommons/base/container/optional.py
pycommons/base/exception/__init__.py
pycommons/base/function/__init__.py
pycommons/base/function/comparator.py
pycommons/base/function/consumer.py
pycommons/base/function/function.py
pycommons/base/function/interface.py
pycommons/base/function/predicate.py
pycommons/base/function/runnable.py
pycommons/base/function/supplier.py
pycommons/base/maps/__init__.py
pycommons/base/maps/maps.py
pycommons/base/streams/__init__.py
pycommons/base/streams/iterator.py
pycommons/base/streams/stream.py
pycommons/base/streams/streams.py
pycommons/base/synchronized.py
pycommons/base/threading/__init__.py
pycommons/base/threading/context.py
pycommons/base/utils/__init__.py
pycommons/base/utils/objectutils.py
pycommons/base/utils/utils.py
pycommons/py.typed
pycommons_base-0.0.9.dist-info/LICENSE
pycommons_base-0.0.9.dist-info/METADATA
pycommons_base-0.0.9.dist-info/WHEEL
pycommons_base-0.0.9.dist-info/RECORD
